contagion/__init__.py
contagion/contagion.py
tests/__init__.py
tests/test_contagion.py
contagion-1.3.3.dist-info/LICENSE.md
contagion-1.3.3.dist-info/METADATA
contagion-1.3.3.dist-info/WHEEL
contagion-1.3.3.dist-info/top_level.txt
contagion-1.3.3.dist-info/RECORD
