Metadata-Version: 2.1
Name: contagion
Version: 1.3.3
Summary: a Python package for node immunization and network contagion simulation
Home-page: https://github.com/lucasmccabe/contagion
Author: Lucas McCabe
Author-email: lucas.mccabe@jhu.edu
License: UNKNOWN
Platform: UNKNOWN
Classifier: Programming Language :: Python :: 3
Classifier: License :: OSI Approved :: MIT License
Classifier: Operating System :: OS Independent
Requires-Python: >=3.6
